desafio_python_dio/__init__.py
desafio_python_dio/final/__init__.py
desafio_python_dio/final/encaixa.py
desafio_python_dio/final/numero_primo.py
desafio_python_dio/final/vetor.py
desafio_python_dio/inicial/__init__.py
desafio_python_dio/inicial/conversao_tempo.py
desafio_python_dio/inicial/media.py
desafio_python_dio/inicial/triangulo.py
desafio_python_dio/intermediario/__init__.py
desafio_python_dio/intermediario/crescente_decrescente.py
desafio_python_dio/intermediario/numeros_positivos.py
desafio_python_dio/intermediario/resto_divisao.py
desafio_python_dio-0.0.1.dist-info/METADATA
desafio_python_dio-0.0.1.dist-info/WHEEL
desafio_python_dio-0.0.1.dist-info/top_level.txt
desafio_python_dio-0.0.1.dist-info/RECORD
