Metadata-Version: 2.1
Name: desafio-python-dio
Version: 0.0.1
Summary: Pacote do Desafio de Projeto com base nos desafios de códigos do Bootcamp Cognizant Data Engineer 2
Home-page: https://github.com/ericscunha/desafio-python-pkg-dio
Author: Eric Cunha
Author-email: ericscunha@hotmail.com
License: UNKNOWN
Platform: UNKNOWN
